[
{"total_index":"589","statis_day":"20150601","name":"合租","play_index":"6202","play_rate_index":"1342","cat_rank":"51.4","cat_name":"其他"},
{"total_index":"6262","statis_day":"20150601","name":"亲亲","play_index":"6262","play_rate_index":"6262","cat_rank":"51.9","cat_name":"办公"},
{"total_index":"54","statis_day":"20150601","name":"爱情","play_index":"6201","play_rate_index":"1.2362","cat_rank":"43.3","cat_name":"娱乐"},
{"total_index":"33","statis_day":"20150601","name":"无线网WIFI登陆客户端","play_index":"6262","play_rate_index":"6262","cat_rank":"40.2","cat_name":"安全"},
{"total_index":"6262","statis_day":"20150601","name":"防灾市场","play_index":"6262","play_rate_index":"6262","cat_rank":"83.6","cat_name":"导航"},
{"total_index":"1482","statis_day":"20150601","name":"LoveLive偶像祭","play_index":"6205","play_rate_index":"2.2187","cat_rank":"255","cat_name":"战略"},
{"total_index":"2440","statis_day":"20150601","name":"平安","play_index":"6203","play_rate_index":"2262","cat_rank":"17.0","cat_name":"教育"},
{"total_index":"6215","statis_day":"20150601","download_index":"6201","name":"易班","play_index":"6201","play_rate_index":"2362","cat_rank":"65.4","cat_name":"教育"},
{"total_index":"6262","statis_day":"20150601","name":"中国影视","play_index":"6262","play_rate_index":"6262","cat_rank":"84.2","cat_name":"教育"},
{"total_index":"6262","statis_day":"20150601","name":"艾","play_index":"6262","play_rate_index":"6262","cat_rank":"20.1","cat_name":"新闻"},
{"total_index":"6237","statis_day":"20150601","name":"天翼云","play_index":"6201","play_rate_index":"1.0538","cat_rank":"63.4","cat_name":"生活"},
{"total_index":"1558","statis_day":"20150601","name":"动感","play_index":"6203","play_rate_index":"222","cat_rank":"11.0","cat_name":"社交"},
{"total_index":"881","statis_day":"20150601","name":"黑白","play_index":"6202","play_rate_index":"256","cat_rank":"13.6","cat_name":"社交"},
{"total_index":"830","statis_day":"20150601","name":"家","play_index":"6203","play_rate_index":"257","cat_rank":"14.0","cat_name":"社交"},
{"total_index":"65","statis_day":"20150601","name":"口袋","play_index":"6201","play_rate_index":"383","cat_rank":"21.0","cat_name":"社交"},
{"total_index":"6262","statis_day":"20150601","name":"第一","play_index":"6262","play_rate_index":"6262","cat_rank":"57.8","cat_name":"社交"},
{"total_index":"6262","statis_day":"20150601","name":"窝","play_index":"6262","play_rate_index":"6262","cat_rank":"73.5","cat_name":"社交"},
{"total_index":"6262","statis_day":"20150601","name":"华科社区","play_index":"6262","play_rate_index":"6262","cat_rank":"87.3","cat_name":"社交"},
{"total_index":"6262","statis_day":"20150601","name":"河南师大通","play_index":"6262","play_rate_index":"6262","cat_rank":"89.5","cat_name":"社交"},
{"total_index":"6262","statis_day":"20150601","name":"足球","play_index":"6262","play_rate_index":"6262","cat_rank":"90.4","cat_name":"社交"},
{"total_index":"6262","statis_day":"20150601","name":"中国矿业大学虚拟","play_index":"6262","play_rate_index":"6262","cat_rank":"95.1","cat_name":"系统"},
{"total_index":"6262","statis_day":"20150601","name":"62后美女风","play_index":"6262","play_rate_index":"6262","cat_rank":"76.1","cat_name":"视频"},
{"total_index":"1610","statis_day":"20150601","name":"纯情","play_index":"6205","play_rate_index":"979","cat_rank":"46.0","cat_name":"角色"},
{"total_index":"6262","statis_day":"20150601","name":"触手","play_index":"6262","play_rate_index":"6262","cat_rank":"31.3","cat_name":"购物"},
{"total_index":"6262","statis_day":"20150601","name":"通","play_index":"6262","play_rate_index":"6262","cat_rank":"32.4","cat_name":"通讯"},
{"total_index":"6262","statis_day":"20150601","name":"动弹","play_index":"6262","play_rate_index":"6262","cat_rank":"38.1","cat_name":"通讯"},
{"total_index":"6262","statis_day":"20150601","name":"xx","play_index":"6262","play_rate_index":"6262","cat_rank":"41.8","cat_name":"通讯"}
]